nextcord/ext/help_commands/__init__.py
nextcord/ext/help_commands/errors.py
nextcord/ext/help_commands/paginated.py
nextcord_ext_help_commands-0.0.1.dist-info/LICENSE
nextcord_ext_help_commands-0.0.1.dist-info/METADATA
nextcord_ext_help_commands-0.0.1.dist-info/WHEEL
nextcord_ext_help_commands-0.0.1.dist-info/top_level.txt
nextcord_ext_help_commands-0.0.1.dist-info/RECORD
