Metadata-Version: 2.1
Name: nextcord-ext-help-commands
Version: 0.0.1
Summary: An extension module for pre-built custom help commands
Home-page: https://github.com/nextcord/nextcord-ext-help-commands
Author: Nextcord Developers
License: MIT
Project-URL: Bug Tracker, https://github.com/nextcord/nextcord-ext-help-commands/issues
Requires-Python: >=3.8.0
License-File: LICENSE
Provides-Extra: docs
Requires-Dist: sphinx ; extra == 'docs'
Requires-Dist: sphinxcontrib-trio ; extra == 'docs'
Requires-Dist: sphinx-book-theme ; extra == 'docs'
Requires-Dist: sphinx-autobuild ; extra == 'docs'
Provides-Extra: menus
Requires-Dist: nextcord-ext-menus ; extra == 'menus'
